treq/__init__.py
treq/_agentspy.py
treq/_multipart.py
treq/_types.py
treq/_version.py
treq/api.py
treq/auth.py
treq/client.py
treq/content.py
treq/cookies.py
treq/multipart.py
treq/py.typed
treq/response.py
treq/testing.py
treq/test/__init__.py
treq/test/test_agentspy.py
treq/test/test_api.py
treq/test/test_auth.py
treq/test/test_client.py
treq/test/test_content.py
treq/test/test_cookies.py
treq/test/test_multipart.py
treq/test/test_response.py
treq/test/test_testing.py
treq/test/test_treq_integration.py
treq/test/util.py
treq/test/local_httpbin/__init__.py
treq/test/local_httpbin/child.py
treq/test/local_httpbin/parent.py
treq/test/local_httpbin/shared.py
treq/test/local_httpbin/test/__init__.py
treq/test/local_httpbin/test/test_child.py
treq/test/local_httpbin/test/test_parent.py
treq/test/local_httpbin/test/test_shared.py
treq-24.9.1.dist-info/LICENSE
treq-24.9.1.dist-info/METADATA
treq-24.9.1.dist-info/WHEEL
treq-24.9.1.dist-info/top_level.txt
treq-24.9.1.dist-info/RECORD
