Metadata-Version: 2.1
Name: treq
Version: 24.9.1
Summary: High-level Twisted HTTP Client API
Home-page: https://github.com/twisted/treq
Author: David Reid
Author-email: dreid@dreid.org
Maintainer: Tom Most
Maintainer-email: twm@freecog.net
License: MIT/X
Classifier: Development Status :: 5 - Production/Stable
Classifier: Intended Audience :: Developers
Classifier: License :: OSI Approved :: MIT License
Classifier: Operating System :: OS Independent
Classifier: Framework :: Twisted
Classifier: Programming Language :: Python
Classifier: Programming Language :: Python :: 3.8
Classifier: Programming Language :: Python :: 3.9
Classifier: Programming Language :: Python :: 3.10
Classifier: Programming Language :: Python :: 3.11
Classifier: Programming Language :: Python :: 3.12
Classifier: Programming Language :: Python :: 3.13
Classifier: Programming Language :: Python :: Implementation :: CPython
Classifier: Programming Language :: Python :: Implementation :: PyPy
Requires-Python: >=3.7
License-File: LICENSE
Requires-Dist: incremental
Requires-Dist: requests>=2.1.0
Requires-Dist: hyperlink>=21.0.0
Requires-Dist: Twisted[tls]>=22.10.0
Requires-Dist: attrs
Requires-Dist: typing_extensions>=3.10.0
Provides-Extra: dev
Requires-Dist: pep8; extra == "dev"
Requires-Dist: pyflakes; extra == "dev"
Requires-Dist: httpbin==0.7.0; extra == "dev"
Requires-Dist: werkzeug==2.0.3; extra == "dev"
Provides-Extra: docs
Requires-Dist: sphinx<7.0.0; extra == "docs"
